{"fajrAdhan": "05:38 AM", "duhrIqamah": "01:00 PM", "fromDate": "11/3/2019", "ishaAdhan": "06:44 PM", "taraweeh": null, "fajrIqamah": "06:00 AM", "hijriAdjustmentValue": 0, "sunrise": "06:47 AM", "prayerName": "Maghrib", "maghribIqamah": "05:40 PM", "firstJummahIqamah": "01:30 PM", "duhrAdhan": "12:11 PM", "nextDayFajrAdhan": "05:39 AM", "jummahDate": "11/8/2019", "asrIqamah": "04:00 PM", "nextDayFajrIqamah": "06:00 AM", "clientID": "1", "secondJummahIqamah": "02:45 PM", "secondsInCountDown": "5392", "asrAdhan": "03:13 PM", "secondJummahKhateeb": "Br. Sajid Ibrahimee", "adjustedHijriDate": null, "firstJummahAdhan": "01:00 PM", "firstJummahKhateeb": "Sh. Yaser Birjas", "hijriDate": null, "maghribAdhan": "05:35 PM", "ishaIqamah": "07:45 PM", "secondJummahAdhan": "02:15 PM"}